gltfutils/__init__.py
gltfutils/tests/__init__.py
gltfutils/tests/test_gltfutils.py
gltfutils-0.0.1.dist-info/LICENSE
gltfutils-0.0.1.dist-info/METADATA
gltfutils-0.0.1.dist-info/WHEEL
gltfutils-0.0.1.dist-info/top_level.txt
gltfutils-0.0.1.dist-info/RECORD
