Metadata-Version: 2.1
Name: gltfutils
Version: 0.0.1
Summary: A set of python libraries for reading, manipulating, and saving gltf files.
Home-page: UNKNOWN
Author: springtangent
Author-email: springtangent42@gmail.com
License: UNKNOWN
Platform: UNKNOWN
Classifier: Programming Language :: Python :: 3
Classifier: License :: OSI Approved :: MIT License
Classifier: Operating System :: OS Independent
Classifier: Development Status :: 2 - Pre-Alpha
Classifier: Intended Audience :: Developers
Classifier: License :: OSI Approved :: MIT License
Classifier: Natural Language :: English
Classifier: Topic :: Artistic Software
Classifier: Topic :: Multimedia :: Graphics :: 3D Modeling
Requires-Python: >=3.6
Requires-Dist: python-datauri (>=0.2.8)
